purex/__init__.py
purex/cli.py
purex/core.py
purex-0.1.2.dist-info/METADATA
purex-0.1.2.dist-info/WHEEL
purex-0.1.2.dist-info/entry_points.txt
purex-0.1.2.dist-info/licenses/LICENSE
purex-0.1.2.dist-info/RECORD
