Metadata-Version: 2.4
Name: purex
Version: 0.1.2
Summary: PuReX - Pull Request data eXtractor
Project-URL: Homepage, https://github.com/j0m0k0/PuReX
Project-URL: Documentation, https://j0m0k0.github.io/PuReX
Project-URL: Repository, https://github.com/j0m0k0/PuReX.git
Project-URL: Issues, https://github.com/j0m0k0/PuReX/issues
Project-URL: Changelog, https://github.com/j0m0k0/PuReX/blob/master/CHANGELOG.md
Author-email: Javad Mokhtari Koushyar <javadmokhtari@outlook.com>
License-Expression: MIT
License-File: LICENSE
Classifier: Development Status :: 3 - Alpha
Classifier: Intended Audience :: Developers
Classifier: Programming Language :: Python :: 3
Classifier: Programming Language :: Python :: 3.8
Classifier: Programming Language :: Python :: 3.9
Classifier: Programming Language :: Python :: 3.10
Classifier: Programming Language :: Python :: 3.11
Classifier: Programming Language :: Python :: 3.12
Classifier: Programming Language :: Python :: 3.13
Classifier: Programming Language :: Python :: 3.14
Classifier: Topic :: Software Development :: Libraries
Requires-Python: >=3.8
Requires-Dist: click>=8.1.8
Requires-Dist: httpx>=0.28.1
Requires-Dist: rich>=14.0.0
Provides-Extra: all
Requires-Dist: sphinx>=7.1.2; extra == 'all'
Provides-Extra: docs
Requires-Dist: sphinx>=7.1.2; extra == 'docs'
